README
setup.py
pynfsn/__init__.py
pynfsn/pynfsn.py
pynfsn.egg-info/PKG-INFO
pynfsn.egg-info/SOURCES.txt
pynfsn.egg-info/dependency_links.txt
pynfsn.egg-info/top_level.txt